{
    "hotTracks": {
        "title": "From Our Editors",
        "results": [
            {
                "name": "Today’s Hits",
                "songs": [
                    {
                        "id": "dI3xkL7qUAc",
                        "title": "Doja Cat - Need To Know (Official Video)",
                        "channelTitle": "dojacatVEVO",
                        "channelId": "UCpTaAz_BxtkUB1qc8JTU_7g",
                        "publishedAt": "2021-06-11T14:00:11Z",
                        "duration": "PT3M40S",
                        "viewCount": "60585082"
                    },
                    {
                        "id": "yWHrYNP6j4k",
                        "title": "The Kid LAROI, Justin Bieber - Stay (Lyrics)",
                        "channelTitle": "7clouds",
                        "channelId": "UCNqFDjYTexJDET3rPDrmJKg",
                        "publishedAt": "2021-07-14T16:55:01Z",
                        "duration": "PT2M20S",
                        "viewCount": "13619339"
                    },
                    {
                        "id": "6tsu2oeZJgo",
                        "title": "Olivia Rodrigo - traitor (Lyric Video)",
                        "channelTitle": "OliviaRodrigoVEVO",
                        "channelId": "UCxE5jEls-T0QtlTHT8lI1lw",
                        "publishedAt": "2021-05-21T04:00:02Z",
                        "duration": "PT3M50S",
                        "viewCount": "55329558"
                    },
                    {
                        "id": "mRD0-GxqHVo",
                        "title": "Glass Animals - Heat Waves (Official Video)",
                        "channelTitle": "GlassAnimalsVEVO",
                        "channelId": "UCOMLtULLvoymORim06O1vaw",
                        "publishedAt": "2020-06-29T18:30:09Z",
                        "duration": "PT3M56S",
                        "viewCount": "36591381"
                    }
                ]
            },
            {
                "name": "R&B Now",
                "songs": [
                    {
                        "id": "SlPhMPnQ58k",
                        "title": "Maroon 5 - Memories (Official Video)",
                        "channelTitle": "Maroon5VEVO",
                        "channelId": "UCN1hnUccO4FD5WfM7ithXaw",
                        "publishedAt": "2019-10-08T14:00:10Z",
                        "duration": "PT3M16S",
                        "viewCount": "756951952"
                    },
                    {
                        "id": "PAFAfhod9TU",
                        "title": "H.E.R. - Damage (Official Video)",
                        "channelTitle": "HERMusicVEVO",
                        "channelId": "UCQT3bmChpmnR5ThhY_ewoOQ",
                        "publishedAt": "2020-10-21T14:00:10Z",
                        "duration": "PT3M45S",
                        "viewCount": "67880294"
                    }
                ]
            },
            {
                "name": "danceXL",
                "songs": [
                    {
                        "id": "tpoveIuHVOg",
                        "title": "King Topher, MUNNDAY – Pressure(ft. MAO)",
                        "channelTitle": "Astralwerks Records",
                        "channelId": "UCpyaRZ-FSkiI1NqEZAiNpMw",
                        "publishedAt": "2021-04-30T04:30:12Z",
                        "duration": "PT2M47S",
                        "viewCount": "124957"
                    }
                ]
            }
        ]
    },
    "newReleases": {
        "title": "新着ミュージック",
        "results": []
    },
    "topAlbums": {
        "title": "Top Albums",
        "results": [
            {
                "name": "Editorial",
                "songs": [
                    {
                        "id": "_rs52auqcmE",
                        "title": "Joyner Lucas - I Love (ADHD)",
                        "channelTitle": "Joyner Lucas",
                        "channelId": "UCUebubwSuTHfHjWJI4gCS9A",
                        "publishedAt": "2018-10-17T16:40:26Z",
                        "duration": "PT3M29S",
                        "viewCount": "75257393"
                    },
                    {
                        "id": "AqaQsL-8I_M",
                        "title": "Megan Thee Stallion - Cry Baby (feat. DaBaby) [Official Video]",
                        "channelTitle": "Megan Thee Stallion",
                        "channelId": "UCKrdjiuS66yXOdEZ_cOD_TA",
                        "publishedAt": "2021-02-04T02:30:09Z",
                        "duration": "PT3M1S",
                        "viewCount": "81587552"
                    }
                ]
            },
            {
                "name": "STRANGER(Special Edition) - EP",
                "songs": [
                    {
                        "id": "yWHrYNP6j4k",
                        "title": "The Kid LAROI, Justin Bieber - Stay (Lyrics)",
                        "channelTitle": "7clouds",
                        "channelId": "UCNqFDjYTexJDET3rPDrmJKg",
                        "publishedAt": "2021-07-14T16:55:01Z",
                        "duration": "PT2M20S",
                        "viewCount": "13619339"
                    }
                ]
            },
            {
                "name": "Queendom - The 6th Mini Album - EP",
                "songs": [
                    {
                        "id": "c9RzZpV460k",
                        "title": "Red Velvet 레드벨벳 'Queendom' MV",
                        "channelTitle": "SMTOWN",
                        "channelId": "UCEf_Bc-KVd7onSeifS3py9g",
                        "publishedAt": "2021-08-16T09:00:48Z",
                        "duration": "PT3M10S",
                        "viewCount": "37101268"
                    }
                ]
            },
            {
                "name": "THE BOOK",
                "songs": [
                    {
                        "id": "DuDX6wNfjqc",
                        "title": "Daft Punk - Epilogue",
                        "channelTitle": "Daft Punk",
                        "channelId": "UC_kRDKYrUlrbtrSiyu5Tflg",
                        "publishedAt": "2021-02-22T14:21:45Z",
                        "duration": "PT7M58S",
                        "viewCount": "26612505"
                    },
                    {
                        "id": "vcGbefQBvJ4",
                        "title": "YOASOBI「アンコール」Official Music Video",
                        "channelTitle": "Ayase / YOASOBI",
                        "channelId": "UCvpredjG93ifbCP1Y77JyFA",
                        "publishedAt": "2021-01-18T14:00:09Z",
                        "duration": "PT4M42S",
                        "viewCount": "35546132"
                    },
                    {
                        "id": "kzdJkT4kp-A",
                        "title": "YOASOBI「ハルジオン」Official Music Video",
                        "channelTitle": "Ayase / YOASOBI",
                        "channelId": "UCvpredjG93ifbCP1Y77JyFA",
                        "publishedAt": "2020-05-11T11:00:11Z",
                        "duration": "PT3M23S",
                        "viewCount": "59947581"
                    },
                    {
                        "id": "sAuEeM_6zpk",
                        "title": "YOASOBI「あの夢をなぞって」 Official Music Video",
                        "channelTitle": "Ayase / YOASOBI",
                        "channelId": "UCvpredjG93ifbCP1Y77JyFA",
                        "publishedAt": "2020-01-18T12:00:13Z",
                        "duration": "PT4M",
                        "viewCount": "36988836"
                    },
                    {
                        "id": "8iuLXODzL04",
                        "title": "YOASOBI「たぶん」Official Music  Video",
                        "channelTitle": "Ayase / YOASOBI",
                        "channelId": "UCvpredjG93ifbCP1Y77JyFA",
                        "publishedAt": "2020-07-20T11:00:13Z",
                        "duration": "PT4M24S",
                        "viewCount": "39083819"
                    },
                    {
                        "id": "Y4nEEZwckuU",
                        "title": "YOASOBI「群青」Official Music Video",
                        "channelTitle": "Ayase / YOASOBI",
                        "channelId": "UCvpredjG93ifbCP1Y77JyFA",
                        "publishedAt": "2020-12-01T11:00:11Z",
                        "duration": "PT4M23S",
                        "viewCount": "52622738"
                    },
                    {
                        "id": "vd3IlOjSUGQ",
                        "title": "YOASOBI「ハルカ」Official Music Video",
                        "channelTitle": "Ayase / YOASOBI",
                        "channelId": "UCvpredjG93ifbCP1Y77JyFA",
                        "publishedAt": "2020-12-18T11:00:10Z",
                        "duration": "PT4M5S",
                        "viewCount": "27036450"
                    },
                    {
                        "id": "x8VYWazR5mE",
                        "title": "YOASOBI「夜に駆ける」 Official Music Video",
                        "channelTitle": "Ayase / YOASOBI",
                        "channelId": "UCvpredjG93ifbCP1Y77JyFA",
                        "publishedAt": "2019-11-16T13:00:11Z",
                        "duration": "PT4M36S",
                        "viewCount": "242154550"
                    }
                ]
            }
        ]
    },
    "topSongs": {
        "name": "Top Songs",
        "songs": [
            {
                "id": "CuklIb9d3fI",
                "title": "BTS (방탄소년단) 'Permission to Dance' Official MV",
                "channelTitle": "HYBE LABELS",
                "channelId": "UC3IZKseVpdzPSBaWxBxundA",
                "publishedAt": "2021-07-09T03:59:12Z",
                "duration": "PT5M",
                "viewCount": "269728976"
            },
            {
                "id": "AqaQsL-8I_M",
                "title": "Megan Thee Stallion - Cry Baby (feat. DaBaby) [Official Video]",
                "channelTitle": "Megan Thee Stallion",
                "channelId": "UCKrdjiuS66yXOdEZ_cOD_TA",
                "publishedAt": "2021-02-04T02:30:09Z",
                "duration": "PT3M1S",
                "viewCount": "81587552"
            },
            {
                "id": "WMweEpGlu_U",
                "title": "BTS (방탄소년단) 'Butter' Official MV",
                "channelTitle": "HYBE LABELS",
                "channelId": "UC3IZKseVpdzPSBaWxBxundA",
                "publishedAt": "2021-05-21T03:46:13Z",
                "duration": "PT3M3S",
                "viewCount": "521564565"
            },
            {
                "id": "yXZd7xVdpJ0",
                "title": "優里 - ドライフラワー / THE FIRST TAKE",
                "channelTitle": "THE FIRST TAKE",
                "channelId": "UC9zY_E8mcAo_Oq772LEZq8Q",
                "publishedAt": "2020-10-30T13:00:13Z",
                "duration": "PT5M12S",
                "viewCount": "72719669"
            },
            {
                "id": "gdZLi9oWNZg",
                "title": "BTS (방탄소년단) 'Dynamite' Official MV",
                "channelTitle": "HYBE LABELS",
                "channelId": "UC3IZKseVpdzPSBaWxBxundA",
                "publishedAt": "2020-08-21T03:58:10Z",
                "duration": "PT3M44S",
                "viewCount": "1215674883"
            },
            {
                "id": "TcLLpZBWsck",
                "title": "Fujii Kaze - Kirari (Official Video)",
                "channelTitle": "Fujii Kaze",
                "channelId": "UCNIy6zQyP7SuLEIaiwymfUA",
                "publishedAt": "2021-05-21T13:00:11Z",
                "duration": "PT4M1S",
                "viewCount": "22053537"
            },
            {
                "id": "yWHrYNP6j4k",
                "title": "The Kid LAROI, Justin Bieber - Stay (Lyrics)",
                "channelTitle": "7clouds",
                "channelId": "UCNqFDjYTexJDET3rPDrmJKg",
                "publishedAt": "2021-07-14T16:55:01Z",
                "duration": "PT2M20S",
                "viewCount": "13619339"
            },
            {
                "id": "x8VYWazR5mE",
                "title": "YOASOBI「夜に駆ける」 Official Music Video",
                "channelTitle": "Ayase / YOASOBI",
                "channelId": "UCvpredjG93ifbCP1Y77JyFA",
                "publishedAt": "2019-11-16T13:00:11Z",
                "duration": "PT4M36S",
                "viewCount": "242154550"
            },
            {
                "id": "dy90tA3TT1c",
                "title": "YOASOBI「怪物」Official Music Video　(YOASOBI - Monster)",
                "channelTitle": "Ayase / YOASOBI",
                "channelId": "UCvpredjG93ifbCP1Y77JyFA",
                "publishedAt": "2021-01-13T13:00:11Z",
                "duration": "PT3M29S",
                "viewCount": "127791987"
            },
            {
                "id": "q09Gs6e5XVI",
                "title": "変態紳士クラブ - YOKAZE (Official Music Video)",
                "channelTitle": "変態紳士クラブ",
                "channelId": "UCMI5tfhifxlSOOh1ErnfJuw",
                "publishedAt": "2020-05-29T12:00:11Z",
                "duration": "PT4M32S",
                "viewCount": "19837639"
            },
            {
                "id": "YnSW8ian29w",
                "title": "【Ado】踊",
                "channelTitle": "Ado",
                "channelId": "UCln9P4Qm3-EAY4aiEPmRwEA",
                "publishedAt": "2021-04-27T11:00:14Z",
                "duration": "PT3M29S",
                "viewCount": "70383259"
            },
            {
                "id": "Y4nEEZwckuU",
                "title": "YOASOBI「群青」Official Music Video",
                "channelTitle": "Ayase / YOASOBI",
                "channelId": "UCvpredjG93ifbCP1Y77JyFA",
                "publishedAt": "2020-12-01T11:00:11Z",
                "duration": "PT4M23S",
                "viewCount": "52622738"
            },
            {
                "id": "zkZARKFuzNQ",
                "title": "Awesome City Club / 勿忘  (MUSIC VIDEO)",
                "channelTitle": "Awesome City Club ‖オーサムシティクラブ",
                "channelId": "UCW66DYvzKs5bmcCqjMqT3-w",
                "publishedAt": "2021-01-27T12:00:11Z",
                "duration": "PT4M33S",
                "viewCount": "38556457"
            },
            {
                "id": "_rs52auqcmE",
                "title": "Joyner Lucas - I Love (ADHD)",
                "channelTitle": "Joyner Lucas",
                "channelId": "UCUebubwSuTHfHjWJI4gCS9A",
                "publishedAt": "2018-10-17T16:40:26Z",
                "duration": "PT3M29S",
                "viewCount": "75257393"
            },
            {
                "id": "kMcawQWipSM",
                "title": "Buddy - Trouble On Central (Official Video)",
                "channelTitle": "BuddyVEVO",
                "channelId": "UCKqTO6M56djXJBjKfwJJo3A",
                "publishedAt": "2018-07-20T04:00:06Z",
                "duration": "PT3M13S",
                "viewCount": "4838941"
            },
            {
                "id": "Zy_KuTFwot4",
                "title": "平井 大 / Stand by me, Stand by you.（Lyric Video）",
                "channelTitle": "平井 大",
                "channelId": "UCOXlVW6fGmawr3LR154FlEg",
                "publishedAt": "2020-09-09T03:00:10Z",
                "duration": "PT3M28S",
                "viewCount": "43518259"
            },
            {
                "id": "-CrGCR4RuWg",
                "title": "Bluma to Lunch",
                "channelTitle": "BLOOM VASE - Topic",
                "channelId": "UCHAXrJraS1OucvsblMrhxXg",
                "publishedAt": "2020-12-18T10:05:18Z",
                "duration": "PT2M40S",
                "viewCount": "17132670"
            },
            {
                "id": "WAMxwRtNrPY",
                "title": "Novelbright - ツキミソウ [Official Music Video]",
                "channelTitle": "Novelbright",
                "channelId": "UCIJAlAYCNN8RACtDDsy9K6g",
                "publishedAt": "2020-12-11T13:00:12Z",
                "duration": "PT5M17S",
                "viewCount": "26793141"
            },
            {
                "id": "1DPldNasDgY",
                "title": "back number - 怪盗 (日本テレビ系 水曜ドラマ「恋はDeepに」主題歌)",
                "channelTitle": "back number",
                "channelId": "UCgipy6-EqjT-1BCDndXX1PA",
                "publishedAt": "2021-05-24T11:00:14Z",
                "duration": "PT3M23S",
                "viewCount": "14167524"
            },
            {
                "id": "gsT6eKsnT0M",
                "title": "DISH// (北村匠海) - 猫 / THE FIRST TAKE",
                "channelTitle": "THE FIRST TAKE",
                "channelId": "UC9zY_E8mcAo_Oq772LEZq8Q",
                "publishedAt": "2020-03-20T13:00:11Z",
                "duration": "PT5M34S",
                "viewCount": "149996284"
            },
            {
                "id": "mfwdvhYIGtw",
                "title": "平井 大 / 題名のない今日（Lyric Video）",
                "channelTitle": "平井 大",
                "channelId": "UCOXlVW6fGmawr3LR154FlEg",
                "publishedAt": "2021-01-27T03:02:24Z",
                "duration": "PT3M30S",
                "viewCount": "12493214"
            },
            {
                "id": "VfATdDI3604",
                "title": "もう少しだけ",
                "channelTitle": "YOASOBI - Topic",
                "channelId": "UCI6B8NkZKqlFWoiC_xE-hzA",
                "publishedAt": "2021-05-09T11:12:29Z",
                "duration": "PT3M41S",
                "viewCount": "16950565"
            },
            {
                "id": "Qp3b-RXtz4w",
                "title": "【Ado】うっせぇわ",
                "channelTitle": "Ado",
                "channelId": "UCln9P4Qm3-EAY4aiEPmRwEA",
                "publishedAt": "2020-10-23T11:00:11Z",
                "duration": "PT3M23S",
                "viewCount": "170494481"
            },
            {
                "id": "1tk1pqwrOys",
                "title": "廻廻奇譚 - Eve MV",
                "channelTitle": "E ve",
                "channelId": "UCUXfRsEIJ9xO1DT7TbEWksw",
                "publishedAt": "2020-11-20T10:00:00Z",
                "duration": "PT3M44S",
                "viewCount": "158874771"
            },
            {
                "id": "kzdJkT4kp-A",
                "title": "YOASOBI「ハルジオン」Official Music Video",
                "channelTitle": "Ayase / YOASOBI",
                "channelId": "UCvpredjG93ifbCP1Y77JyFA",
                "publishedAt": "2020-05-11T11:00:11Z",
                "duration": "PT3M23S",
                "viewCount": "59947581"
            },
            {
                "id": "vd3IlOjSUGQ",
                "title": "YOASOBI「ハルカ」Official Music Video",
                "channelTitle": "Ayase / YOASOBI",
                "channelId": "UCvpredjG93ifbCP1Y77JyFA",
                "publishedAt": "2020-12-18T11:00:10Z",
                "duration": "PT4M5S",
                "viewCount": "27036450"
            },
            {
                "id": "R7wI90H6Wuc",
                "title": "川崎鷹也-魔法の絨毯【OFFICIAL MUSIC VIDEO】",
                "channelTitle": "川崎鷹也【公式】",
                "channelId": "UCZwXiIKBc9ok5QsOqXk5kiw",
                "publishedAt": "2020-09-13T10:33:49Z",
                "duration": "PT3M20S",
                "viewCount": "44878800"
            },
            {
                "id": "9IHwqdz8Xhw",
                "title": "BTS (방탄소년단) 'Stay Gold' Official MV",
                "channelTitle": "HYBE LABELS",
                "channelId": "UC3IZKseVpdzPSBaWxBxundA",
                "publishedAt": "2020-06-26T08:59:11Z",
                "duration": "PT4M16S",
                "viewCount": "196463240"
            },
            {
                "id": "vcGbefQBvJ4",
                "title": "YOASOBI「アンコール」Official Music Video",
                "channelTitle": "Ayase / YOASOBI",
                "channelId": "UCvpredjG93ifbCP1Y77JyFA",
                "publishedAt": "2021-01-18T14:00:09Z",
                "duration": "PT4M42S",
                "viewCount": "35546132"
            },
            {
                "id": "zFT3f9biz68",
                "title": "BTS (방탄소년단) 'Film out' Official MV",
                "channelTitle": "HYBE LABELS",
                "channelId": "UC3IZKseVpdzPSBaWxBxundA",
                "publishedAt": "2021-04-01T15:00:09Z",
                "duration": "PT3M49S",
                "viewCount": "159102468"
            },
            {
                "id": "MBdVXkSdhwU",
                "title": "BTS (방탄소년단) 'DNA' Official MV",
                "channelTitle": "HYBE LABELS",
                "channelId": "UC3IZKseVpdzPSBaWxBxundA",
                "publishedAt": "2017-09-18T09:00:02Z",
                "duration": "PT4M16S",
                "viewCount": "1329454399"
            },
            {
                "id": "ZeIGVnkYX04",
                "title": "napori",
                "channelTitle": "Vaundy - Topic",
                "channelId": "UC8_Ag6BVp43Vmrx6eillK9g",
                "publishedAt": "2020-05-26T10:06:33Z",
                "duration": "PT3M24S",
                "viewCount": "22576167"
            },
            {
                "id": "4DxL6IKmXx4",
                "title": "LiSA 『炎』 -MUSiC CLiP-",
                "channelTitle": "LiSA Official YouTube",
                "channelId": "UCqEfdEvLG5oQWNYlDQrGlKw",
                "publishedAt": "2020-10-13T03:00:07Z",
                "duration": "PT5M2S",
                "viewCount": "209492783"
            },
            {
                "id": "ReCnlwVZj1M",
                "title": "Official髭男dism - 115万キロのフィルム［Official Audio］",
                "channelTitle": "Official髭男dism",
                "channelId": "UC3vg17IZ1IV73xx069jG44w",
                "publishedAt": "2018-03-16T09:00:01Z",
                "duration": "PT5M24S",
                "viewCount": "54214045"
            },
            {
                "id": "XsX3ATc3FbA",
                "title": "BTS (방탄소년단) '작은 것들을 위한 시 (Boy With Luv) (feat. Halsey)' Official MV",
                "channelTitle": "HYBE LABELS",
                "channelId": "UC3IZKseVpdzPSBaWxBxundA",
                "publishedAt": "2019-04-12T09:00:02Z",
                "duration": "PT4M13S",
                "viewCount": "1329578476"
            },
            {
                "id": "0xSiBpUdW4E",
                "title": "あいみょん - マリーゴールド【OFFICIAL MUSIC VIDEO】",
                "channelTitle": "あいみょん",
                "channelId": "UCG8MvaPCa2ecKH3GZyFxduA",
                "publishedAt": "2018-07-17T23:00:01Z",
                "duration": "PT5M22S",
                "viewCount": "252421293"
            },
            {
                "id": "7WZ1Kt3zraY",
                "title": "米津玄師 - Pale Blue",
                "channelTitle": "米津玄師",
                "channelId": "UCUCeZaZeJbEYAAzvMgrKOPQ",
                "publishedAt": "2021-06-04T13:54:55Z",
                "duration": "PT5M22S",
                "viewCount": "37531729"
            },
            {
                "id": "UM9XNpgrqVk",
                "title": "怪獣の花唄 / Vaundy ： MUSIC VIDEO",
                "channelTitle": "Vaundy",
                "channelId": "UC1FQWQ3y3-e8l1pCtWhJt5A",
                "publishedAt": "2020-07-02T15:00:10Z",
                "duration": "PT3M53S",
                "viewCount": "11644514"
            },
            {
                "id": "323j5BRFi7s",
                "title": "マカロニえんぴつ「恋人ごっこ」MV",
                "channelTitle": "murffin discs",
                "channelId": "UC1-EP9cKVrNQqvG-drnDA7Q",
                "publishedAt": "2020-02-06T08:58:38Z",
                "duration": "PT3M26S",
                "viewCount": "26672463"
            },
            {
                "id": "sOiMD45QGLs",
                "title": "【Ado】ギラギラ",
                "channelTitle": "Ado",
                "channelId": "UCln9P4Qm3-EAY4aiEPmRwEA",
                "publishedAt": "2021-02-14T11:00:16Z",
                "duration": "PT4M37S",
                "viewCount": "68954400"
            },
            {
                "id": "9qfPF4fpiHE",
                "title": "優里 『ピーターパン』Official Music Video（フル）",
                "channelTitle": "優里 Official YouTube Channel",
                "channelId": "UCBNVZPlWoR7oArfzJNrK9yw",
                "publishedAt": "2020-09-02T13:00:14Z",
                "duration": "PT3M57S",
                "viewCount": "20866900"
            },
            {
                "id": "sAuEeM_6zpk",
                "title": "YOASOBI「あの夢をなぞって」 Official Music Video",
                "channelTitle": "Ayase / YOASOBI",
                "channelId": "UCvpredjG93ifbCP1Y77JyFA",
                "publishedAt": "2020-01-18T12:00:13Z",
                "duration": "PT4M",
                "viewCount": "36988836"
            },
            {
                "id": "-5q5mZbe3V8",
                "title": "BTS (방탄소년단) 'Life Goes On' Official MV",
                "channelTitle": "HYBE LABELS",
                "channelId": "UC3IZKseVpdzPSBaWxBxundA",
                "publishedAt": "2020-11-20T04:58:11Z",
                "duration": "PT3M51S",
                "viewCount": "376276733"
            }
        ]
    }
}